config/__init__.py
config/asgi.py
config/settings.py
config/urls.py
config/wsgi.py
example/__init__.py
example/admin.py
example/apps.py
example/models.py
example/tests.py
example/urls.py
example/views.py
example/migrations/__init__.py
nhif/__init__.py
nhif/api_call.py
nhif/token.py
django_nhif-0.0.1.dist-info/LICENSE
django_nhif-0.0.1.dist-info/METADATA
django_nhif-0.0.1.dist-info/WHEEL
django_nhif-0.0.1.dist-info/top_level.txt
django_nhif-0.0.1.dist-info/RECORD
