Metadata-Version: 2.1
Name: django-nhif
Version: 0.0.1
Summary: A Django application which assist on integration of your web application with NHIF System with easy step
Home-page: https://github.com/devmed/django-nhif
Author: Medson Naftali
Author-email: medsonnaftal@gmail.com
License: UNKNOWN
Project-URL: Bug Tracker, https://github.com/devmed/django-nhif/issues
Platform: UNKNOWN
Classifier: Programming Language :: Python :: 3
Classifier: License :: OSI Approved :: MIT License
Classifier: Operating System :: OS Independent
License-File: LICENSE
Requires-Dist: requests
